jsonextra/__init__.py
jsonextra/json_extra.py
jsonextra-0.4.0.dist-info/LICENSE
jsonextra-0.4.0.dist-info/METADATA
jsonextra-0.4.0.dist-info/WHEEL
jsonextra-0.4.0.dist-info/top_level.txt
jsonextra-0.4.0.dist-info/zip-safe
jsonextra-0.4.0.dist-info/RECORD
