Metadata-Version: 2.1
Name: jsonextra
Version: 0.4.0
Summary: JSON Extra | JSON that gives you extra datetime, uuid and bytes data types
Home-page: https://github.com/den4uk/jsonextra
Author: Denis Sazonov
Author-email: den@saz.lt
License: MIT License
Keywords: json,uuid,datetime,date,bytes
Platform: UNKNOWN
Classifier: Programming Language :: Python :: 3
Classifier: License :: OSI Approved :: MIT License
Classifier: Operating System :: OS Independent
Requires-Python: >=3.5
License-File: LICENSE
Requires-Dist: python-dateutil
